[
  {
    "ContainingType": "DotNetWebApp.Controllers.HomeController",
    "Method": "Error",
    "RelativePath": "Home/Error",
    "HttpMethod": "",
    "IsController": true,
    "Order": 0,
    "Parameters": [],
    "ReturnTypes": []
  },
  {
    "ContainingType": "DotNetWebApp.Controllers.HomeController",
    "Method": "GetUsers",
    "RelativePath": "Home/GetUsers",
    "HttpMethod": "GET",
    "IsController": true,
    "Order": 0,
    "Parameters": [],
    "ReturnTypes": [
      {
        "Type": "System.Collections.Generic.IEnumerable\u00601[[DotNetWebApp.Models.CustomUser, DotNetWebApp, Version=1.0.0.0, Culture=neutral, PublicKeyToken=null]]",
        "MediaTypes": [
          "text/plain",
          "application/json",
          "text/json"
        ],
        "StatusCode": 200
      }
    ]
  },
  {
    "ContainingType": "DotNetWebApp.Controllers.HomeController",
    "Method": "Index",
    "RelativePath": "Home/Index",
    "HttpMethod": "",
    "IsController": true,
    "Order": 0,
    "Parameters": [],
    "ReturnTypes": []
  },
  {
    "ContainingType": "DotNetWebApp.Controllers.HomeController",
    "Method": "Privacy",
    "RelativePath": "Home/Privacy",
    "HttpMethod": "",
    "IsController": true,
    "Order": 0,
    "Parameters": [],
    "ReturnTypes": []
  }
]